hyperglass_agent/.gitignore
hyperglass_agent/__init__.py
hyperglass_agent/api/__init__.py
hyperglass_agent/api/web.py
hyperglass_agent/cli/__init__.py
hyperglass_agent/cli/actions.py
hyperglass_agent/cli/commands.py
hyperglass_agent/cli/echo.py
hyperglass_agent/cli/exceptions.py
hyperglass_agent/cli/static.py
hyperglass_agent/config.py
hyperglass_agent/console.py
hyperglass_agent/constants.py
hyperglass_agent/example_config.yaml
hyperglass_agent/exceptions.py
hyperglass_agent/execute.py
hyperglass_agent/log.py
hyperglass_agent/models/__init__.py
hyperglass_agent/models/_formatters.py
hyperglass_agent/models/_utils.py
hyperglass_agent/models/commands.py
hyperglass_agent/models/general.py
hyperglass_agent/models/request.py
hyperglass_agent/nos_utils/__init__.py
hyperglass_agent/nos_utils/bird.py
hyperglass_agent/nos_utils/frr.py
hyperglass_agent/payload.py
hyperglass_agent/util.py
hyperglass_agent-0.1.6.dist-info/entry_points.txt
hyperglass_agent-0.1.6.dist-info/LICENSE
hyperglass_agent-0.1.6.dist-info/WHEEL
hyperglass_agent-0.1.6.dist-info/METADATA
hyperglass_agent-0.1.6.dist-info/RECORD
